LICENSE.txt
README.rst
setup.py
agent/agentClient.py
agent/logger.py
agent/messageClass.py
agent/tools.py
agent/example/config.py
agent/example/demoReceiveMessage.py
agent/example/main.py
agent/example/simulator.py
agent/packages/__init__.py
agent/packages/base.py
agent/packages/receive.py
agent/packages/send.py
agent/packages/message/__init__.py
agent/packages/message/base.py
agent/packages/message/receive/__init__.py
agent/packages/message/receive/finishWork.py
agent/packages/message/receive/startWork.py
agent/packages/message/send/__init__.py
agent/packages/message/send/finishWorkFail.py
agent/packages/message/send/finishWorkSuccess.py
agent/packages/message/send/initializedAck.py
agent/packages/message/send/startWorkFail.py
agent/packages/message/send/startWorkSuccess.py
avatar_agent.egg-info/PKG-INFO
avatar_agent.egg-info/SOURCES.txt
avatar_agent.egg-info/dependency_links.txt
avatar_agent.egg-info/requires.txt
avatar_agent.egg-info/top_level.txt