Metadata-Version: 2.1
Name: avatar-agent
Version: 0.1.2
Summary: pip3 install avatar-agent
Home-page: https://github.com/guige?tab=repositories
Author: 鬼阁
Author-email: shuming.wsm@alibaba-inc.com
License: MIT
Platform: UNKNOWN
Classifier: License :: OSI Approved :: MIT License
Classifier: Programming Language :: Python
Classifier: Programming Language :: Python :: 3
Classifier: Programming Language :: Python :: 3.6
Classifier: Programming Language :: Python :: Implementation :: CPython
Classifier: Programming Language :: Python :: Implementation :: PyPy
Requires-Python: >=3.6.0
License-File: LICENSE.txt
